flowbite_classes/__init__.py
flowbite_classes/apps.py
flowbite_classes/forms.py
flowbite_classes/monkey_patch.py
flowbite_classes/renderers.py
flowbite_classes/widgets.py
flowbite_classes/templates/flowbite_classes/fields/checkbox.html
flowbite_classes/templates/flowbite_classes/fields/date.html
flowbite_classes/templates/flowbite_classes/fields/fields.html
flowbite_classes/templates/flowbite_classes/fields/file.html
flowbite_classes/templates/flowbite_classes/fields/other.html
flowbite_classes/templates/flowbite_classes/fields/radio.html
flowbite_classes/templates/flowbite_classes/fields/select.html
flowbite_classes/templates/flowbite_classes/fields/temp_radio.html
flowbite_classes/templates/flowbite_classes/fields/time.html
flowbite_classes/templates/flowbite_classes/widgets/numeric_incremental.html
codi_cooperatiu_internal_tools-0.2.1.dist-info/METADATA
codi_cooperatiu_internal_tools-0.2.1.dist-info/WHEEL
codi_cooperatiu_internal_tools-0.2.1.dist-info/top_level.txt
codi_cooperatiu_internal_tools-0.2.1.dist-info/RECORD
