Metadata-Version: 2.1
Name: codi-cooperatiu-internal-tools
Version: 0.2.1
Summary: Codi Cooperatiu internal tools
Project-URL: homepage, https://github.com/codicoop/codi-cooperatiu-internal-tools
Project-URL: repository, https://github.com/codicoop/codi-cooperatiu-internal-tools
Keywords: django,forms,flowbite
Classifier: Programming Language :: Python :: 3
Classifier: Framework :: Django
Classifier: Operating System :: OS Independent
Requires-Python: >=3.10
Requires-Dist: django>=5.0a1
